test_package/main.py
test_package_15551/__init__.py
test_package_15551/main.py
test_package_15551-1.0.0.dist-info/METADATA
test_package_15551-1.0.0.dist-info/WHEEL
test_package_15551-1.0.0.dist-info/top_level.txt
test_package_15551-1.0.0.dist-info/RECORD
