Metadata-Version: 2.1
Name: test-package-15551
Version: 1.0.0
Summary: A test library
Home-page: https://github.com/remla23-team09/lib
Author: Zhiyong Zhu
Author-email: z13913982280@gmail.com
License: MIT
Requires-Dist: requests
